<?xml version="1.0" encoding="utf-8" ?>
<dwsync>
<file name="direktori.html" server="ilindenstruga.com.mk" local="128862072000000000" remote="128862072000000000" />
<file name="dogovori.html" server="ilindenstruga.com.mk" local="128862072000000000" remote="128862072000000000" />
<file name="drdejnosti.html" server="ilindenstruga.com.mk" local="128862072000000000" remote="128862072000000000" />
<file name="finpodatoci.html" server="ilindenstruga.com.mk" local="128862072000000000" remote="128862072000000000" />
<file name="galerija.html" server="ilindenstruga.com.mk" local="128862072000000000" remote="128862072000000000" />
<file name="galerijaNisko.html" server="ilindenstruga.com.mk" local="128862072000000000" remote="128862072000000000" />
<file name="hidro.html" server="ilindenstruga.com.mk" local="128862072000000000" remote="128862072000000000" />
<file name="index.html" server="ilindenstruga.com.mk" local="128862072000000000" remote="128862072000000000" />
<file name="kontakt.html" server="ilindenstruga.com.mk" local="128862072000000000" remote="128862072000000000" />
<file name="lokalni.html" server="ilindenstruga.com.mk" local="128862072000000000" remote="128862072000000000" />
<file name="menager.html" server="ilindenstruga.com.mk" local="129228016785084783" remote="129228016800000000" />
<file name="nisko.html" server="ilindenstruga.com.mk" local="128862072000000000" remote="128862072000000000" />
<file name="tehnicki.html" server="ilindenstruga.com.mk" local="128862072000000000" remote="128862072000000000" />
<file name="tehnoloska.html" server="ilindenstruga.com.mk" local="128862072000000000" remote="128862072000000000" />
<file name="visoko.html" server="ilindenstruga.com.mk" local="128862072000000000" remote="128862072000000000" />
<file name="zanas.html" server="ilindenstruga.com.mk" local="128862072000000000" remote="128862072000000000" />
</dwsync>