<?xml version="1.0" encoding="utf-8" ?>
<dwsync>
<file name="Home1.jpg" server="ilindenstruga.com.mk" local="128862072000000000" remote="128862072000000000" />
<file name="Intro.swf" server="ilindenstruga.com.mk" local="128862072000000000" remote="128862072000000000" />
<file name="LogoSplash.png" server="ilindenstruga.com.mk" local="128862072000000000" remote="128862072000000000" />
<file name="adress.png" server="ilindenstruga.com.mk" local="128862072000000000" remote="128862072000000000" />
<file name="alati.png" server="ilindenstruga.com.mk" local="128862072000000000" remote="128862072000000000" />
<file name="arrow.gif" server="ilindenstruga.com.mk" local="128862072000000000" remote="128862072000000000" />
<file name="banka.png" server="ilindenstruga.com.mk" local="128862072000000000" remote="128862072000000000" />
<file name="direktori.png" server="ilindenstruga.com.mk" local="128862072000000000" remote="128862072000000000" />
<file name="finansiski.png" server="ilindenstruga.com.mk" local="128862072000000000" remote="128862072000000000" />
<file name="homemala.png" server="ilindenstruga.com.mk" local="128862072000000000" remote="128862072000000000" />
<file name="mail.png" server="ilindenstruga.com.mk" local="128862072000000000" remote="128862072000000000" />
<file name="menagerskitim.png" server="ilindenstruga.com.mk" local="128862072000000000" remote="128862072000000000" />
<file name="meni.gif" server="ilindenstruga.com.mk" local="128862072000000000" remote="128862072000000000" />
<file name="meni1.gif" server="ilindenstruga.com.mk" local="128862072000000000" remote="128862072000000000" />
<file name="pat.gif" server="ilindenstruga.com.mk" local="128862072000000000" remote="128862072000000000" />
<file name="telefon.png" server="ilindenstruga.com.mk" local="128862072000000000" remote="128862072000000000" />
<file name="transport.png" server="ilindenstruga.com.mk" local="128862072000000000" remote="128862072000000000" />
<file name="zanas.png" server="ilindenstruga.com.mk" local="128862072000000000" remote="128862072000000000" />
</dwsync>